odoo/addons/account_cash_discount_payment/README.rst
odoo/addons/account_cash_discount_payment/__init__.py
odoo/addons/account_cash_discount_payment/__manifest__.py
odoo/addons/account_cash_discount_payment/i18n/account_cash_discount_payment.pot
odoo/addons/account_cash_discount_payment/i18n/fr.po
odoo/addons/account_cash_discount_payment/models/__init__.py
odoo/addons/account_cash_discount_payment/models/account_move.py
odoo/addons/account_cash_discount_payment/models/account_move_line.py
odoo/addons/account_cash_discount_payment/models/account_payment_line.py
odoo/addons/account_cash_discount_payment/readme/CONTRIBUTORS.rst
odoo/addons/account_cash_discount_payment/readme/DESCRIPTION.rst
odoo/addons/account_cash_discount_payment/static/description/icon.png
odoo/addons/account_cash_discount_payment/static/description/index.html
odoo/addons/account_cash_discount_payment/tests/__init__.py
odoo/addons/account_cash_discount_payment/tests/common.py
odoo/addons/account_cash_discount_payment/tests/test_account_cash_discount_payment.py
odoo/addons/account_cash_discount_payment/views/account_move_line.xml
odoo/addons/account_cash_discount_payment/views/account_payment_line.xml
odoo/addons/account_cash_discount_payment/wizards/__init__.py
odoo/addons/account_cash_discount_payment/wizards/account_payment_line_create.py
odoo/addons/account_cash_discount_payment/wizards/account_payment_line_create.xml
odoo14_addon_account_cash_discount_payment-14.0.1.0.2.dist-info/METADATA
odoo14_addon_account_cash_discount_payment-14.0.1.0.2.dist-info/WHEEL
odoo14_addon_account_cash_discount_payment-14.0.1.0.2.dist-info/top_level.txt
odoo14_addon_account_cash_discount_payment-14.0.1.0.2.dist-info/RECORD
